cmem_plugin_splitfile/__init__.py
cmem_plugin_splitfile/doc/__init__.py
cmem_plugin_splitfile/doc/splitfile_doc.md
cmem_plugin_splitfile/plugin_splitfile.py
cmem_plugin_splitfile/resource_parameter_type.py
cmem_plugin_splitfile/splitfile.svg
cmem_plugin_splitfile-1.1.0.dist-info/METADATA
cmem_plugin_splitfile-1.1.0.dist-info/WHEEL
cmem_plugin_splitfile-1.1.0.dist-info/licenses/LICENSE
cmem_plugin_splitfile-1.1.0.dist-info/RECORD
