Metadata-Version: 2.4
Name: cmem-plugin-splitfile
Version: 1.1.0
Summary: Split a text file into parts of the same filesize
License: Apache-2.0
License-File: LICENSE
Keywords: eccenca Corporate Memory,plugin
Author: eccenca GmbH
Author-email: cmempy-developer@eccenca.com
Requires-Python: >=3.13,<4.0
Classifier: Development Status :: 4 - Beta
Classifier: Environment :: Plugins
Classifier: License :: OSI Approved :: Apache Software License
Classifier: Programming Language :: Python :: 3
Classifier: Programming Language :: Python :: 3.13
Classifier: Programming Language :: Python :: 3.14
Requires-Dist: cmem-cmempy (>=25.3.0,<26.0.0)
Requires-Dist: cmem-plugin-base (>=4.12.1,<5.0.0)
Requires-Dist: filesplit (>=4.1.0,<5.0.0)
Requires-Dist: pathvalidate (>=3.2.3,<4.0.0)
Requires-Dist: requests (>=2.32.5,<3.0.0)
Project-URL: Homepage, https://github.com/eccenca/cmem-plugin-splitfile
